ProjectScaffold/__init__.py
ProjectScaffold/cli.py
ProjectScaffold/scaffold.py
ProjectScaffold/templates/backend/django_template/manage.py
ProjectScaffold/templates/backend/django_template/requirements.txt
ProjectScaffold/templates/backend/express_template/app.js
ProjectScaffold/templates/backend/express_template/package.json
ProjectScaffold/templates/backend/fastapi_template/main.py
ProjectScaffold/templates/backend/fastapi_template/requirements.txt
ProjectScaffold/templates/backend/flask_template/app.py
ProjectScaffold/templates/backend/flask_template/requirements.txt
ProjectScaffold/templates/backend/flask_template/static/style.css
ProjectScaffold/templates/backend/flask_template/templates/index.html
ProjectScaffold/templates/backend/nodejs_template/index.js
ProjectScaffold/templates/backend/nodejs_template/package.json
ProjectScaffold/templates/backend/springboot_template/README.md
ProjectScaffold/templates/db/mongodb_template.json
ProjectScaffold/templates/db/mysql.sql
ProjectScaffold/templates/db/postgres.sql
ProjectScaffold/templates/db/sqlite.sql
ProjectScaffold/templates/frontend/angular_template/README.md
ProjectScaffold/templates/frontend/react_template/package.json
ProjectScaffold/templates/frontend/react_template/src/App.jsx
ProjectScaffold/templates/frontend/svelte_template/README.md
ProjectScaffold/templates/frontend/vanilla_template/app.js
ProjectScaffold/templates/frontend/vanilla_template/index.html
ProjectScaffold/templates/frontend/vanilla_template/style.css
ProjectScaffold/templates/frontend/vue_template/README.md
projectscaffold-0.1.0.dist-info/licenses/LICENSE
projectscaffold-0.1.0.dist-info/METADATA
projectscaffold-0.1.0.dist-info/WHEEL
projectscaffold-0.1.0.dist-info/entry_points.txt
projectscaffold-0.1.0.dist-info/top_level.txt
projectscaffold-0.1.0.dist-info/RECORD
