Metadata-Version: 2.4
Name: ProjectScaffold
Version: 0.1.0
Summary: CLI tool to scaffold backend, frontend, and DB projects in MVC architecture
Home-page: https://github.com/maria2021831011/ProjectScaffold
Author: maria2021831011
Author-email: ritukhan534@gmail.com
Project-URL: Documentation, https://github.com/maria2021831011/ProjectScaffold#readme
Project-URL: Source, https://github.com/maria2021831011/ProjectScaffold
Project-URL: Tracker, https://github.com/maria2021831011/ProjectScaffold/issues
Keywords: scaffold,cli,mvc,project-generator,python
Classifier: Development Status :: 4 - Beta
Classifier: Programming Language :: Python :: 3
Classifier: Programming Language :: Python :: 3.9
Classifier: Programming Language :: Python :: 3.10
Classifier: Programming Language :: Python :: 3.11
Classifier: License :: OSI Approved :: MIT License
Classifier: Operating System :: OS Independent
Requires-Python: >=3.9
License-File: LICENSE
Requires-Dist: click
Dynamic: license-file
Dynamic: requires-dist
Dynamic: requires-python
